{"forum": {"content": "\u6211\u6c92\u6709\u5f88\u5e25\u4f46\u6211\u5c31\u662f\u559c\u6b61\u81ea\u62cd\uff01\uff01", "images": ["http://filestoresg1.beetalkmobile.com:8081/file/de0362a620cca441261ed316620d28e4", "http://filestoresg1.beetalkmobile.com:8081/file/6ac8ca44ac8ec21f91aabdf1dda19c8c", "http://filestoresg1.beetalkmobile.com:8081/file/e62050411d99306468342f3c501d749c"], "urls": [], "title": "\u5c31\u662f\u611b\u81ea\u62cd"}, "threadStatus": 0, "regionId": 886, "barStatus": 0, "barId": 4, "postBy": {"utc": 1444961144000, "level": 2, "location": "\u82b1\u84ee\u7e23\u00b7\u53f0\u7063", "avatar": "http://filestoresg1.beetalkmobile.com:8081/file/756743287791816704", "name": "FB:\u738b\u99ac\u8000"}, "id": 2330169}
