{"forum": {"content": "\u9858\u610f\u4f86\u4ea4\u500b\u670b\u53cb\u55ce\uff1f", "images": ["http://filestoresg1.beetalkmobile.com:8081/file/5ace9dba35d7af554c8e9a8c24d08b49"], "urls": [], "title": "\u8a66\u8a66\u5427\u2026"}, "threadStatus": 1, "regionId": 886, "barStatus": 0, "barId": 205, "postBy": {"utc": 1448911260000, "level": 8, "location": "\u65b0\u7af9\u5e02\u00b7\u53f0\u7063", "avatar": "http://filestoresg1.beetalkmobile.com:8081/file/-8053001281010612293", "name": "R\u7fd4"}, "id": 2627972}
