{"forum": {"content": "\u4e00\u500b\u7537\u751f\u8ddf\u559c\u6b61\u7684\u5973\u751f\u544a\u767d\u4e86<br />\u4f46\u544a\u767d\u4e4b\u5f8c\u7537\u751f\u537b\u5728\u4e5f\u6c92\u8ddf\u5973\u751f\u806f\u7d61<br />\u5973\u751f\u6703\u600e\u9ebc\u60f3?<br />\u6703\u60f3\u8ddf\u7537\u751f\u806f\u7d61\u55ce\uff1f<br />\u800c\u5973\u751f\u4e5f\u6709\u559c\u6b61\u7537\u751f\u800c\u8868\u793a\u9806\u5176\u81ea\u7136", "images": ["http://filestoresg1.beetalkmobile.com:8081/file/29a9bf7437bfbd9712844e6a1ec40af5"], "urls": [], "title": "\u544a\u767d..."}, "threadStatus": 1, "regionId": 886, "barStatus": 0, "barId": 13, "postBy": {"utc": 1441922085000, "level": 2, "location": "\u53f0\u5317\u5e02\u00b7\u53f0\u7063", "avatar": "http://filestoresg1.beetalkmobile.com:8081/file/8441171781963519661", "name": "\u5225\u8b93Eason\u4e0d\u958b\u5fc3\ud83d\ude0d\ud83d\ude0d\ud83d\ude0d"}, "id": 2095749}
