{"forum": {"content": "\u6709\u4e00\u4e9b\u4eba \u6df1\u611b\u904e\u5225\u64c1\u6709\u4e5f\u597d<br />\u6709\u4e00\u4e9b\u8a71 \u90a3\u6642\u5019\u5225\u7576\u771f\u5c31\u597d", "images": [], "urls": [{"url": "https://youtu.be/Wci-uzY7_Js", "thumbUrl": "https://i.ytimg.com/vi/Wci-uzY7_Js/hqdefault.jpg", "description": "-\u6578\u4f4d\u5e73\u53f0- KKBOX http://kkbox.fm/Ja0MlB Omusic http://goo.gl/ZMShL9 iTunes http://goo.gl/dMNtKp Spotify ", "title": "\u5b89\u5fc3\u4e9e Amber_An\u300a\u65b0\u5bbfA New Destination \u300bOfficial Music Video (\u5076\u50cf\u5287\u300c\u59b9\u59b9\u300d\u7247\u5c3e\u66f2"}], "title": "\u5509\u2026\u53c8\u54ed\u4e86"}, "threadStatus": 0, "regionId": 886, "barStatus": 0, "barId": 54, "postBy": {"utc": 1445442513000, "level": 6, "location": "\u6843\u5712\u5e02\u00b7\u53f0\u7063", "avatar": "http://filestoresg1.beetalkmobile.com:8081/file/-3267109740457867886", "name": "\u8431\u59ae\u82b1\ud83c\udf39"}, "id": 2370748}
