{"forum": {"content": "\u9019\u88cf\u4e5f\u6709\u4eba\u662f\u5c08\u6ac3\u4e0a\u73ed\u7684\u55ce\ud83d\ude09", "images": ["http://filestoresg1.beetalkmobile.com:8081/file/d2844707258f2a551b5eee34194719af", "http://filestoresg1.beetalkmobile.com:8081/file/892a335717a3528a12704f5d96749c79", "http://filestoresg1.beetalkmobile.com:8081/file/30acb1c76a0cd463aaf6eca5049fe9ec"], "urls": [], "title": "Hello \u5927\u5bb6\u597d\u6211\u662f\u6ac3\u59d0"}, "threadStatus": 0, "regionId": 886, "barStatus": 0, "barId": 32, "postBy": {"utc": 1448419523000, "level": 2, "location": "\u53f0\u4e2d\u5e02\u00b7\u53f0\u7063", "avatar": "http://filestoresg1.beetalkmobile.com:8081/file/-5104348590616636917", "name": "Wennie"}, "id": 2592157}
