{"forum": {"content": "\u770b\u4e86\u597d\u591a\u4ebapo\u7537\u53cb\u6587\u771f\u7684\u53ef\u4ee5\u5fb5\u5230\u55ce\uff1f<br />\u7537\u751f\u5230\u5e95\u6703\u5148\u770b\u5973\u751f\u54ea\u9ede\u624d\u6703\u9078\u64c7\u4ea4\u5f80\uff1f\u800c\u4e14\u9060\u8ddd\u96e2\u4f60\u5011\u771f\u7684\u53ef\u63a5\u53d7\u9ebb", "images": ["http://filestoresg1.beetalkmobile.com:8081/file/8e94ab9e7b5012938b42db3b35f6f064"], "urls": [], "title": "\u611f\u89ba\u8ddf\u7591\u554f-_-!-_-!"}, "threadStatus": 1, "regionId": 886, "barStatus": 0, "barId": 205, "postBy": {"utc": 1441191197000, "level": 12, "location": "", "avatar": "http://filestoresg1.beetalkmobile.com:8081/file/-543812950222852120", "name": "\u83f2\u83f2I love you"}, "id": 2038586}
