{"forum": {"content": "<br />\u61c9\u5ba2\u4eba\u8981\u6c42\u7684\u6b3e\u5f0f\u5148\u8a66\u756b\u5979\u8981\u7684\u67f4\u72ac\u5716\u6848\uff5e\u6211\u5c45\u7136\u6c92\u627e\u5716\u6191\u7a7a\u756b==\u4e00\u9ede\u4e5f\u4e0d\u50cf\u67f4\u72ac", "images": ["http://filestoresg1.beetalkmobile.com:8081/file/8b761ac2591d850303af60990330e483"], "urls": [], "title": "\u8c93\u72d7\u5927\u6230\u7684\u6982\u5ff5\u55ceXD"}, "threadStatus": 0, "regionId": 886, "barStatus": 0, "barId": 733, "postBy": {"utc": 1454000864000, "level": 2, "location": "\u65b0\u5317\u5e02\u00b7\u53f0\u7063", "avatar": "http://filestoresg1.beetalkmobile.com:8081/file/-7480134828669555296", "name": "\u5c41"}, "id": 2997651}
