{"forum": {"content": "\u963f\u963f\u963f\u963f\uff0c\u4e00\u9ede\u90fd\u4e0d\u6210\u719f\u5440\uff5e\ud83d\ude2f\ud83d\ude2f\ud83d\ude2f", "images": ["http://filestoresg1.beetalkmobile.com:8081/file/8f6ed1a42855072104eca9bc99e09a52", "http://filestoresg1.beetalkmobile.com:8081/file/95c249d2dcef4d2faa3dcd3ebf1ffd77", "http://filestoresg1.beetalkmobile.com:8081/file/449d79884883b676fad24ee555fa5456", "http://filestoresg1.beetalkmobile.com:8081/file/444b7bea241968b201159dc2f3061779", "http://filestoresg1.beetalkmobile.com:8081/file/704be691467195cdba2e9822afd746ac"], "urls": [], "title": "\u807d\u8aaa\u59d0\u59d0\u6709\u9ede\u5446"}, "threadStatus": 1, "regionId": 886, "barStatus": 0, "barId": 734, "postBy": {"utc": 1453999404000, "level": 0, "location": "\u53f0\u4e2d\u5e02\u00b7\u53f0\u7063", "avatar": "http://filestoresg1.beetalkmobile.com:8081/file/8746394004262699310", "name": "MAY"}, "id": 2997499}
