{"forum": {"content": "79\u5e7412\u670816\u65e5<br />\u5c04\u624b\u5ea7<br />", "images": ["http://filestoresg1.beetalkmobile.com:8081/file/93e1a6dded1bc6c4f3b6e5b5bc117a89"], "urls": [], "title": "\u6709\u4eba\u8ddf\u6211\u540c\u4e00\u5929\u751f\u65e5\u55ce\uff01"}, "threadStatus": 1, "regionId": 886, "barStatus": 0, "barId": 765, "postBy": {"utc": 1452870928000, "level": 2, "location": "\u65b0\u5317\u5e02\u00b7\u53f0\u7063", "avatar": "http://filestoresg1.beetalkmobile.com:8081/file/-7141330220048495470", "name": "\u6de1\u5b9a\u7965"}, "id": 2914479}
