{"forum": {"content": "\u5927\u5bb6\u53ef\u4ee5\u8aaa\u8aaa\u770b\u81ea\u5df1\u7684\u60f3\u6cd5\u55ce\uff1f<br /><br />\u6216\u662f\u5e7e\u516c\u5206\u5167\u53ef\u4ee5\u63a5\u53d7\u9019\u6a23\uff1f\uff1f", "images": ["http://filestoresg1.beetalkmobile.com:8081/file/61a2fd5f599837a1663bddf8a2b1eed8"], "urls": [], "title": "\u7537\u751f\u6703\u5728\u610f\u81ea\u5df1\u6bd4\u53e6\u4e00\u534a\u77ee\u55ce\uff1f"}, "threadStatus": 0, "regionId": 886, "barStatus": 0, "barId": 205, "postBy": {"utc": 1441112578000, "level": 1, "location": "\u53f0\u4e2d\u5e02\u00b7\u53f0\u7063", "avatar": "http://filestoresg1.beetalkmobile.com:8081/file/1760682055612464541", "name": "\u53f3"}, "id": 2032731}
