{"forum": {"content": "\u8b93\u5b89\u975c\u4e5f\u80fd\u7cbe\u5f69!<br />na\u83dc!", "images": ["http://filestoresg1.beetalkmobile.com:8081/file/9b9c317f17826a2d8034872de403cc0f", "http://filestoresg1.beetalkmobile.com:8081/file/e23060670040591b562975c99c5aa2c6", "http://filestoresg1.beetalkmobile.com:8081/file/802a8f5c7ebe2651924ab6dd6c90d060", "http://filestoresg1.beetalkmobile.com:8081/file/31f7678a1d58b4bf638a4495c73a5e39"], "urls": [], "title": "\u7d50\u69cb\u5168\u6191\u60f3\u50cf\u53bb\u5be6\u73fe"}, "threadStatus": 0, "regionId": 886, "barStatus": 0, "barId": 35, "postBy": {"utc": 1453006843000, "level": 3, "location": "\u65b0\u5317\u5e02\u00b7\u53f0\u7063", "avatar": "http://filestoresg1.beetalkmobile.com:8081/file/8722794092638203456", "name": "\u6c90\u7814\u83dc\u83dc"}, "id": 2923848}
