{"forum": {"content": "\u89ba\u5f97\u559c\u6b61\u9019\u985e\u6771\u897f\u7684\u5973\u5b69\u8d85\u6709\u9b45\u529b\u7684 \u6709\u4eba\u4e5f\u9019\u9ebc\u89ba\u5f97\u55ce\uff1f<br /><br />", "images": ["http://filestoresg1.beetalkmobile.com:8081/file/57596af07ef8ff9459605e8cbeceaa3c", "http://filestoresg1.beetalkmobile.com:8081/file/b71b2cc3b67f7466e308cbb4fcbfa3af", "http://filestoresg1.beetalkmobile.com:8081/file/6159770ad0959547886a45c4d58d6087"], "urls": [], "title": "\u6709\u6c92\u559c\u6b61\u96fb\u73a9\u52d5\u756b\u7684\u5973\u5b69\u5152\u5462\uff1f"}, "threadStatus": 0, "regionId": 886, "barStatus": 0, "barId": 205, "postBy": {"utc": 1449979836000, "level": 2, "location": "\u6843\u5712\u5e02\u00b7\u53f0\u7063", "avatar": "http://filestoresg1.beetalkmobile.com:8081/file/5243728183896373556", "name": "\u963f\u7f85"}, "id": 2706257}
