{"forum": {"content": "\u96d6\u7136\u7121\u6cd5\u5728\u7b2c\u4e00\u6642\u9593\u770b\u5230\u592a\u967d\u5192\u51fa<br />\u982d\u3001\u4f46\u6176\u5e78\u9019\u5929\u7684\u96f2\u5f88\u751f\u52d5\u3001\u4e0d\u6789<br />\u8cbb\u6478\u9ed1\u5f9e\u5e02\u5340\u9a0e\u8eca\u5230\u52a0\u8def\u862d\u9019\u3001\u770b<br />\u5230\u9019\u6a23\u7684\u666f\u8272\u4e00\u5207\u90fd\u5f88\u503c\u5f97.<br />", "images": ["http://filestoresg1.beetalkmobile.com:8081/file/92e79f56278073e0111b3e6142684ee9", "http://filestoresg1.beetalkmobile.com:8081/file/88d5da43dbcc99391f91841f57c00adb", "http://filestoresg1.beetalkmobile.com:8081/file/926ceee0dbc73ed7bbb4ba784c019719", "http://filestoresg1.beetalkmobile.com:8081/file/ea18df4f736c1a5688106f0e711bc46b", "http://filestoresg1.beetalkmobile.com:8081/file/e8e50b495405afb0eeec779bea7b2965", "http://filestoresg1.beetalkmobile.com:8081/file/ff3db669dc92c22239e2811b3e105c63"], "urls": [], "title": "20160101\uff5e\u53f0\u6771\u52a0\u8def\u862d\u65e5\u51fa"}, "threadStatus": 0, "regionId": 886, "barStatus": 0, "barId": 85, "postBy": {"utc": 1451829298000, "level": 35, "location": "\u9ad8\u96c4\u5e02\u00b7\u53f0\u7063", "avatar": "http://filestoresg1.beetalkmobile.com:8081/file/6076586254948177242", "name": "\u7b28\u7b28"}, "id": 2838513}
