{"forum": {"content": "\u53ef\u4ee5\u4f86\u804a\u804a\u5929 \u7d14\u804a\u5929\uff01\u71b1\u60c5\u7684\u4f86\u54e6", "images": ["http://filestoresg1.beetalkmobile.com:8081/file/29eed73f4bb3f30349bbd9d619b2fb94", "http://filestoresg1.beetalkmobile.com:8081/file/d18e6202e3b61c427c68e6f0dfc8b1d0", "http://filestoresg1.beetalkmobile.com:8081/file/44727cc688c29c0459fb7463d476d132"], "urls": [], "title": "\u6559\u670b\u53cb\u56c9\uff5e\u71b1\u60c5\u7684\u4f86\u4f86"}, "threadStatus": 1, "regionId": 886, "barStatus": 0, "barId": 15, "postBy": {"utc": 1443449119000, "level": 2, "location": "\u53f0\u5317\u5e02\u00b7\u53f0\u7063", "avatar": "http://filestoresg1.beetalkmobile.com:8081/file/-2205723665180624382", "name": "\u7537\u53cb"}, "id": 2210548}
