{"forum": {"content": "\u771f\u611b<br />\u7684\u78ba\u4e0d\u597d\u627e<br /><br />\u771f\u611b\u503c\u5f97\u7b49\u5f85<br />\u6c89\u6fb1\u8457\u5fc3<br />\u5148\u611b\u81ea\u5df1 \u5225\u4eba\u624d\u80fd\u5920\u611b\u4f60<br /><br />\u6211\u4e0d\u5e25\u4e0d\u9ad8<br />\u4f46 \u6211\u7b49\u5230\u4e86<br /><br />\u4f60\u5011\u4e5f\u53ef\u4ee5<br />\u5171\u52c9", "images": ["http://filestoresg1.beetalkmobile.com:8081/file/5cb454fe5f5184e987bb408dbe0c4394"], "urls": [], "title": "\u771f\u611b"}, "threadStatus": 0, "regionId": 886, "barStatus": 0, "barId": 20, "postBy": {"utc": 1447432021000, "level": 3, "location": "\u6843\u5712\u5e02\u00b7\u53f0\u7063", "avatar": "http://filestoresg1.beetalkmobile.com:8081/file/-8357181160734435964", "name": "\u5b8b\u5c0f\u5b5f"}, "id": 2520758}
