{"forum": {"content": "\u7da0\u6cb9\u6cb9\u5915\u967d\u904b\u52d5\u8db4<br />\u5927\u81ea\u7136\u7684\u914d\u8272 \u80af\u5b9a\u5c31\u662f\u904b\u52d5\u6700\u597d\u7684\u539f\u52d5\u529b\uff0c\u8212\u5766\u3002\u3002\u3002\u54c8", "images": ["http://filestoresg1.beetalkmobile.com:8081/file/9de395ab1014d5b3af06311f5ed6c50c", "http://filestoresg1.beetalkmobile.com:8081/file/d3048a9f1faef9daa488ad4aca925d0a", "http://filestoresg1.beetalkmobile.com:8081/file/80f188abc6325243739cf393e5b7a911", "http://filestoresg1.beetalkmobile.com:8081/file/526d3b8ea74cdb9aefdffc8d23bc8e28", "http://filestoresg1.beetalkmobile.com:8081/file/8411711934500c93bd3767d9b6e3686d", "http://filestoresg1.beetalkmobile.com:8081/file/2aefc1a9ddf94f35dc0c62c4db18594c"], "urls": [], "title": "\u7da0\u6cb9\u6cb9\u5915\u967d\u904b\u52d5\u8db4\n-3"}, "threadStatus": 0, "regionId": 886, "barStatus": 0, "barId": 77, "postBy": {"utc": 1445596465000, "level": 35, "location": "\u65b0\u5317\u5e02\u00b7\u53f0\u7063", "avatar": "http://filestoresg1.beetalkmobile.com:8081/file/-4070873630783615619", "name": "Sam "}, "id": 2382501}
