{"forum": {"content": "\u9019\u9ebc\u51b7\u7684\u591c\u88e1<br />\u597d\u60f3\u6709\u500b\u4eba\u53ef\u4ee5\u74b0\u62b1....<br /><br />\u975e\u95dc\u60c5\u8272<br />\u611f\u53d7\u4e00\u9ede\u6eab\u5ea6....<br />\u5c0b\u6c42\u4e9b\u8a31\u6eab\u5b58....<br />\u64c1\u62b1\u77ed\u66ab\u6eab\u6696....<br /><br />", "images": ["http://filestoresg1.beetalkmobile.com:8081/file/78c2f91d2d64386dd0be646d670067f2"], "urls": [], "title": "\u4f60/\u59b3\uff0c\u4e5f\u6703\u55ce\uff1f"}, "threadStatus": 1, "regionId": 886, "barStatus": 0, "barId": 13, "postBy": {"utc": 1453583801000, "level": 12, "location": "\u65b0\u5317\u5e02\u00b7\u53f0\u7063", "avatar": "http://filestoresg1.beetalkmobile.com:8081/file/-7906148309229759614", "name": "\u5403\u8ca8\u5927\u53d4~\u8ad2\u54e5"}, "id": 2967439}
