{"forum": {"content": "\u5404\u4f4d\u597d\uff0c\u60f3\u8ddf\u5404\u4f4d\u4ecb\u7d39\u65b0\u64fa\u7684\u5c0f\u6524\u4f4d\uff0c<br />\u5473\u9053\u975e\u5e38\u7f8e\u5473\uff0c\u800c\u4e14\u53c8\u4e7e\u6de8\uff0c\u98df\u6750\u90fd\u9084\u662f\u73fe\u5f04\u7684\uff01\u665a\u4e0a5\u9ede\u6703\u518d\u6b66\u5edf\u95dc\u5e1d\u5edf\u9019\u908a\u64fa\uff5e<br />\u5c31\u9023\u5916\u570b\u4eba\u90fd\u60f3\u5403\u5403\u53f0\u7063\u7684\u5c0f\u5403\ud83d\ude0b\u5fc3\u52d5\u4e86\u55ce\uff5e\u9084\u4e0d\u5feb\u53bb\u54c1\u5690\u4e00\u4e0b\ud83d\ude0b\ud83d\ude0b\ud83d\ude0b\ud83d\ude18\ud83d\ude18\ud83d\ude18", "images": ["http://filestoresg1.beetalkmobile.com:8081/file/7ecf7c93306669b73f5a91f43f97f51e", "http://filestoresg1.beetalkmobile.com:8081/file/1f61e907f72ed0c5fef2ecd7fa9bdd88", "http://filestoresg1.beetalkmobile.com:8081/file/18baea1b7a8e6653fbf29238147848e4", "http://filestoresg1.beetalkmobile.com:8081/file/a1c799aba7f7d76dfd78f2d6ebdf3892", "http://filestoresg1.beetalkmobile.com:8081/file/c9b319dab2c5e00241d89fd2386416ac"], "urls": [], "title": "\u9ad8\u96c4\u6b66\u5edf\u8def\uff0c\u852c\u62cc\u6ef7\u5473\ud83d\ude0b\ud83d\ude0b\ud83d\ude0b"}, "threadStatus": 0, "regionId": 886, "barStatus": 0, "barId": 98, "postBy": {"utc": 1443895420000, "level": 1, "location": "\u9ad8\u96c4\u5e02\u00b7\u53f0\u7063", "avatar": "http://filestoresg1.beetalkmobile.com:8081/file/742176947086203064", "name": "\u7d00\u5148\u751f"}, "id": 2245373}
