{"forum": {"content": "\u81ea\u80a5<br />\u8eab\u9ad8154<br />\u9ad4\u91cd45.1(\u6211\u662f\u80d6\u5b50)<br />bmi 19.02<br />\u9019\u6a23\u7b97\u5b85\u7537\u5973\u795e\u55ce <br />\u53ea\u6709\u5b85\u7537\u6c92\u6709\u5973\u795e(T_T)", "images": ["http://filestoresg1.beetalkmobile.com:8081/file/f530f72ae1bfb5be1543134029bdd6dc", "http://filestoresg1.beetalkmobile.com:8081/file/2676ad40dc6ed1977f059108e7381145", "http://filestoresg1.beetalkmobile.com:8081/file/0fc4e1e44bf0e4d9ed1e9941af4492ca", "http://filestoresg1.beetalkmobile.com:8081/file/cb86a9d2a4fd813193fc701330e15271", "http://filestoresg1.beetalkmobile.com:8081/file/a8f3fcfa76511c401d136801c6c284b5", "http://filestoresg1.beetalkmobile.com:8081/file/32f9fda72e61cea09bdb62c23ee003af"], "urls": [], "title": "\u81ea\u80a5"}, "threadStatus": 0, "regionId": 886, "barStatus": 0, "barId": 32, "postBy": {"utc": 1441131086000, "level": 2, "location": "\u5b9c\u862d\u7e23\u00b7\u53f0\u7063", "avatar": "http://filestoresg1.beetalkmobile.com:8081/file/-599599968689369344", "name": "\u6e38\u6e38\u3002"}, "id": 2034705}
