{"forum": {"content": "\u5c0f\u5f1f\u662f\u756b\u756b\u5b78\u5f92\uff0c\u9019\u662f\u6211\u7b2c\u4e00\u5834\u500b\u5c55\u7684\u5176\u4e2d\u5e7e\u5f35\u5716\uff0c\u90fd\u662f\u670b\u53cb\u7684\u5bf5\u7269\uff0c\u6709\u8208\u8da3\u7684\u5404\u4f4d\u6b61\u8fce\u4f86\u770b\u770b\u5594", "images": ["http://filestoresg1.beetalkmobile.com:8081/file/121697ecf9948e24718921a24ba8f5f6", "http://filestoresg1.beetalkmobile.com:8081/file/9b2f8c530f8fe2dd9e6cc5d99417133c", "http://filestoresg1.beetalkmobile.com:8081/file/40557397a896a0e069839f45d80153dd", "http://filestoresg1.beetalkmobile.com:8081/file/9f6ce31a4c41a30f6a18a6a3ca8a2bc7"], "urls": [], "title": "\u500b\u4eba\u756b\u5c55"}, "threadStatus": 0, "regionId": 886, "barStatus": 0, "barId": 35, "postBy": {"utc": 1452109614000, "level": 1, "location": "\u5b9c\u862d\u7e23\u00b7\u53f0\u7063", "avatar": "http://filestoresg1.beetalkmobile.com:8081/file/-5489271116744097534", "name": "\u7fd4"}, "id": 2859372}
