{"forum": {"content": "\u8aa0\u61c7\u7684\u6b61\u8fce\u52a0\u5165\u2764\ufe0f\ud83d\udc99\ud83d\udc9b\u5973\u58eb\u512a\u5148\ud83d\ude4b<br />\u4e0d\u6015\u6c92\u4eba\u966a\uff0c\u53ea\u6015\u6c92\u4eba\u63ea<br />\u6bcf\u5929\u8b93\u4f60\u804a\u4e0d\u5b8c\u7684\u8a71\u984c<br />\u771f\u5fc3\u8207\u4f60\u4ea4\u670b\u53cb<br />\u6b61\u6deb\u5e25\u54e5\u7f8e\u5973\u52a0\u5165\u5537\u5537\u5537\ud83d\ude0f\ud83d\ude0f\ud83d\ude0f", "images": ["http://filestoresg1.beetalkmobile.com:8081/file/cb72560e180c576e1852d1cf7085cd3c", "http://filestoresg1.beetalkmobile.com:8081/file/32bef0f3550197bd5460fba45763f6b1", "http://filestoresg1.beetalkmobile.com:8081/file/6f691debf11042a7ae03febe5442cc06", "http://filestoresg1.beetalkmobile.com:8081/file/9289b33ba87553cf2e44ea7a55b7ae3d"], "urls": [], "title": "\u760b\u63ea\u5718\ud83c\udf5c\ud83c\udfc4\ud83c\udf7a\ud83c\udf75\ud83c\udf79\u5403\u559d\u73a9\u6a02"}, "threadStatus": 0, "regionId": 886, "barStatus": 0, "barId": 687, "postBy": {"utc": 1442590454000, "level": 6, "location": "\u65b0\u5317\u5e02\u00b7\u53f0\u7063", "avatar": "http://filestoresg1.beetalkmobile.com:8081/file/-9156562405183643954", "name": "Im\ud83c\udf6dMo"}, "id": 2146997}
