{"forum": {"content": "\u4eba\u6c23\u52d5\u756bLoveLive\u7684\u89d2\u8272<br />\u7531ALTER\u9019\u5bb6\u516c\u53f8\u88fd\u4f5c<br /><br />\u7b46\u8005\u5728\u6691\u5047\u671f\u9593\u62cd\u651d\u9019\u96bb\uff0c<br />\u53ef\u4ee5\u8aaa\u662f\u525b\u597d\u6e05\u6dbc\u4e00\u4e0bw<br /><br />\u6b64\u4f5c\u54c1\u982d\u9aee\u7684\u5c64\u6b21\u5f88\u6f02\u4eae\uff1b<br />\u773c\u775b\u7684\u8cbc\u5716\u3001\u7d05\u6688\u3001\u5634\u7684\u908a\u7de3\u548c\u5fae\u5fae\u7684\u9732\u9f52\uff0c\u90fd\u8655\u7406\u7684\u5f88\u597d<br /><br />\u7a0d\u5fae\u7528\u6253\u5149\u896f\u6258\u51fa\u808c\u819a\u8cea\u611f\uff0c\u4ee5\u53ca\u6cf3\u88dd\u7c89\u8272\u6f38\u5c64<br /><br />\u66f4\u591a\u7167\u7247\u548c\u6587\u7ae0:http://home.gamer.com.tw/creationDetail.php?sn=2900050", "images": ["http://filestoresg1.beetalkmobile.com:8081/file/bc6a6787fd7d4cf19f3d76c8e2efc5df", "http://filestoresg1.beetalkmobile.com:8081/file/557fd749965310c5de8a4e1deb90602c", "http://filestoresg1.beetalkmobile.com:8081/file/bb972d8324f180a578f161e0508e7b5c", "http://filestoresg1.beetalkmobile.com:8081/file/e8fb9f47c481bc7a8bf71f78ac42112c", "http://filestoresg1.beetalkmobile.com:8081/file/f5efaf8a97aaac94bc8d9d517993ea91", "http://filestoresg1.beetalkmobile.com:8081/file/e0d48d8e9e6d44c450e6e4ead1435ead"], "urls": [], "title": "[\u958b\u7bb1] Alter \u771f\u59ec"}, "threadStatus": 0, "regionId": 886, "barStatus": 0, "barId": 207, "postBy": {"utc": 1442590137000, "level": 3, "location": "\u53f0\u4e2d\u5e02\u00b7\u53f0\u7063", "avatar": "http://filestoresg1.beetalkmobile.com:8081/file/7144259334245079859", "name": "\u8ab2\u684c\u6905"}, "id": 2146956}
