{"forum": {"content": "\u4e00\u76f4\u90fd\u60f3\u8981\u7167\u9867\u59ca\u59ca\uff0c\u53ef\u662f\u9047\u5230\u7684\u90fd\u662f\u59b9\u59b9<br />\u4f55\u6642\u59ca\u59ca\u624d\u6703\u51fa\u73fe\u5462\uff1f", "images": ["http://filestoresg1.beetalkmobile.com:8081/file/361a975f53c29f6cd388f9a6ab401927", "http://filestoresg1.beetalkmobile.com:8081/file/99e20e6be178295d45787b4acd56e0cc", "http://filestoresg1.beetalkmobile.com:8081/file/1b04068da6a0a7923cdd81e9830aedd7", "http://filestoresg1.beetalkmobile.com:8081/file/67e677eeca9ec380fde266b86944c81b", "http://filestoresg1.beetalkmobile.com:8081/file/914fdc94a407a765bc618b84e29bd995", "http://filestoresg1.beetalkmobile.com:8081/file/4b7c9fbbcbf4a4dd0149808659b41c5a"], "urls": [], "title": "\u5c0b\u627e\u59d0\u5f1f\u6200\u3002"}, "threadStatus": 0, "regionId": 886, "barStatus": 0, "barId": 205, "postBy": {"utc": 1449816449000, "level": 1, "location": "\u53f0\u4e2d\u5e02\u00b7\u53f0\u7063", "avatar": "http://filestoresg1.beetalkmobile.com:8081/file/8765943321029772032", "name": "AlversLi"}, "id": 2693999}
