{"forum": {"content": "   \u611f\u89ba   \u58be\u4e01\u98ef\u5e97\u696d\u5230\u8655\u90fd\u5728\u7f3a\u4eba   <br /><br />      \u7576\u5730\u4eba\u4e5f\u559c\u6b61\u61c9\u5fb5\u64fa\u6524", "images": ["http://filestoresg1.beetalkmobile.com:8081/file/424a21a43cd4fc39e64fa1371eb0baae"], "urls": [], "title": "\u58be\u4e01\u611f\u89ba\u597d\u96e3\u627e\u54e1\u5de5   "}, "threadStatus": 1, "regionId": 886, "barStatus": 0, "barId": 206, "postBy": {"utc": 1451794190000, "level": 3, "location": "\u5c4f\u6771\u7e23\u00b7\u53f0\u7063", "avatar": "http://filestoresg1.beetalkmobile.com:8081/file/4046674482757851658", "name": "\u601d\u8003\u672a\u4f86"}, "id": 2835235}
