{"forum": {"content": "\u5206\u958b\u591a\u4e45\u4e86<br />\u6bcf\u5929\u639b\u5ff5\u8457\uff0c\u5077\u5077\u89c0\u5bdf\u5979\u7684\u751f\u6d3b\u9ede\u9ede\u6ef4\u6ef4<br />\u76f4\u5230\u770b\u898b\u5979\u8207\u4ed6....<br />\u5fb9\u5e95\u6b7b\u5fc3\u4e86\uff0c\u4e0b\u4e00\u6bb5\u53c8\u8a72\u5f9e\u4f55\u958b\u59cb", "images": ["http://filestoresg1.beetalkmobile.com:8081/file/e514bb9d7d3063a003d6b98961663e3e"], "urls": [], "title": "\u7d42\u65bc\u653e\u4e0b\u4e86"}, "threadStatus": 0, "regionId": 886, "barStatus": 0, "barId": 729, "postBy": {"utc": 1452668469000, "level": 2, "location": "", "avatar": "http://filestoresg1.beetalkmobile.com:8081/file/-7956139804124426493", "name": "CK"}, "id": 2898938}
