{"forum": {"content": "\u8ddf\u672c\u63d0\u4e0d\u8d77\u52c1  \u52d5\u52d5\u505c\u505c \u62d6\u4e86\u56db\u500b\u591a\u6708", "images": ["http://filestoresg1.beetalkmobile.com:8081/file/cf48d6aa568266fb6a8d7aa35b9a062a", "http://filestoresg1.beetalkmobile.com:8081/file/ae4bf7289c783f0d3f9291a3f83da6e6", "http://filestoresg1.beetalkmobile.com:8081/file/e16917ab78eef1b9e613329de1a25a75", "http://filestoresg1.beetalkmobile.com:8081/file/2850ec601ae693fdb0dd2eb50d8acbb3"], "urls": [], "title": "\u5b8c\u6210\u4eba\u578b \u5f85\u6c34\u8cbc\u4e7e\u4e0a\u4fdd\u8b77\u6f06 \u4e0b\u4e00\u500b\u5c31\u662f\u5ea7\u9a0e"}, "threadStatus": 0, "regionId": 886, "barStatus": 0, "barId": 207, "postBy": {"utc": 1447375078000, "level": 3, "location": "\u9ad8\u96c4\u5e02\u00b7\u53f0\u7063", "avatar": "http://filestoresg1.beetalkmobile.com:8081/file/7062199482520512858", "name": "\u9670\u5929\u8b93\u4eba\u5f88 \u7169"}, "id": 2515952}
