{"forum": {"content": "\u6709\u4eba\u6703\u53bb\u57fa\u9686\u65b0\u958b\u7684\u5065\u8eab\u623f\u55ce<br />\u7fa9\u4e00\u8def \u7389\u5c71\u9280\u884c\u90a3\u908a", "images": ["http://filestoresg1.beetalkmobile.com:8081/file/a7e83007178d65b47527bbac4df60892", "http://filestoresg1.beetalkmobile.com:8081/file/be067d81068ebf8594f0d0b25d43f0fb"], "urls": [], "title": "\u57fa\u9686\u65b0\u958b\u7684\u5065\u8eab\u623f"}, "threadStatus": 1, "regionId": 886, "barStatus": 0, "barId": 66, "postBy": {"utc": 1441004778000, "level": 3, "location": "\u57fa\u9686\u5e02\u00b7\u53f0\u7063", "avatar": "http://filestoresg1.beetalkmobile.com:8081/file/-5643886642627073274", "name": "Ha"}, "id": 2024310}
