{"forum": {"content": "\u96d6\u7136\u4e0d\u671f\u671b\u592a\u58ef<br />\u4f46\u5c45\u5bb6\u5076\u723e\u7df4\u7df4<br />\u8ffd\u6c42\u8eab\u6750\u4e0d\u8d70\u6a23<br />\u5176\u5be6\u9019\u6a23\u5c31\u5920\u4e86<br />\u7e7c\u7e8c\u4fdd\u6301^_^<br /><br /><br /><br /><br />\u4e0d\u8981\u7b11\u6211<br />\u6211\u77e5\u9053\u6bd4\u6211\u58ef\u7684\u5f88\u591a@_@", "images": ["http://filestoresg1.beetalkmobile.com:8081/file/62516b2c3ab5fd0dc8f0771889f396da", "http://filestoresg1.beetalkmobile.com:8081/file/a533c19e7266be8c17aaa11517722bd8", "http://filestoresg1.beetalkmobile.com:8081/file/08557d7f349aeabc89fbdb590b71fd2a", "http://filestoresg1.beetalkmobile.com:8081/file/75c98f262c9adcb6f1ea6180207bf850", "http://filestoresg1.beetalkmobile.com:8081/file/506067b06fdea9954cb6668866c30b90", "http://filestoresg1.beetalkmobile.com:8081/file/4caba461d1e39eaab06551521cc6043f"], "urls": [], "title": "\u5c31\u662f\u62cd\u56c9"}, "threadStatus": 0, "regionId": 886, "barStatus": 0, "barId": 4, "postBy": {"utc": 1446254211000, "level": 7, "location": "\u53f0\u5357\u5e02\u00b7\u53f0\u7063", "avatar": "http://filestoresg1.beetalkmobile.com:8081/file/-884470238197022057", "name": "\u767d\u9e9f"}, "id": 2433815}
