{"forum": {"content": "\u6b61\u8fce\u5927\u5bb6\u52a0\u5165IG <br />\u2728Dolly\u2728\u670d\u98fe\u5973\u88dd\u914d\u4ef6<br />\ud83d\udd0d\u6b61\u8fce\u641c\u5c0bIG:dolly20151120<br />\ud83d\udd0d\u6b61\u8fce+LINE\uff1adolly20151120", "images": ["http://filestoresg1.beetalkmobile.com:8081/file/6a814210f1a0413ce436b55e8230a54a"], "urls": [], "title": "\u2728Dolly\u2728\u670d\u98fe\u5973\u88dd\u914d\u4ef6 \ud83d\udd0d\u6b61\u8fce\u641c\u5c0bIG:dolly20151120 \ud83d\udd0d\u6b61\u8fce+LINE\uff1adolly20151120"}, "threadStatus": 1, "regionId": 886, "barStatus": 0, "barId": 36, "postBy": {"utc": 1448181254000, "level": 1, "location": "", "avatar": "http://filestoresg1.beetalkmobile.com:8081/file/-8449986551317555716", "name": "Noe"}, "id": 2574839}
