{"forum": {"content": "\u5065\u8eab\u623f\u5925\u4f34", "images": ["http://filestoresg1.beetalkmobile.com:8081/file/431e3fac0d23581e490f6219af218814", "http://filestoresg1.beetalkmobile.com:8081/file/14ad685d13344feba2c35680893d0b39", "http://filestoresg1.beetalkmobile.com:8081/file/23e8c2c58281c327251340957c83420f", "http://filestoresg1.beetalkmobile.com:8081/file/771b7948d1fea3ab1face75208901030", "http://filestoresg1.beetalkmobile.com:8081/file/3cddf1a9f0c3dad806607cacc6e805eb", "http://filestoresg1.beetalkmobile.com:8081/file/7c95cac2b71da3ce6436aeb69acdb39b"], "urls": [], "title": "\u5e73\u5b89\u591c\u4ea4\u63db\u79ae\u7269"}, "threadStatus": 0, "regionId": 886, "barStatus": 0, "barId": 77, "postBy": {"utc": 1451149613000, "level": 8, "location": "\u65b0\u7af9\u5e02\u00b7\u53f0\u7063", "avatar": "http://filestoresg1.beetalkmobile.com:8081/file/3222112229645971933", "name": "\u67e5\u7406big boy"}, "id": 2791953}
