{"forum": {"content": "\u731b\u864e\u51fa\u9598~", "images": ["http://filestoresg1.beetalkmobile.com:8081/file/cb5f4c37dbcef8156105b5bb680dc257", "http://filestoresg1.beetalkmobile.com:8081/file/9738b7e9da065caba66af31856d74f76"], "urls": [], "title": "\u54c8\u5409"}, "threadStatus": 1, "regionId": 886, "barStatus": 0, "barId": 105, "postBy": {"utc": 1441521951000, "level": 6, "location": "Kaohsiung City\u00b7Taiwan", "avatar": "http://filestoresg1.beetalkmobile.com:8081/file/2625562302556341825", "name": "Su"}, "id": 2064230}
