{"forum": {"content": "\u5c4f\u6771-\u9ad8\u6a39\u5340\u7684\u6ce2\u65af\u83ca\u548c\u5411\u65e5\u8475\u82b1\u6d77(\u624b\u6a5f\u62cd\u651d)", "images": ["http://filestoresg1.beetalkmobile.com:8081/file/829ea70a92c9c02dba8b8d1b18b18aa1", "http://filestoresg1.beetalkmobile.com:8081/file/f9b3b882e4c3a0ada1c856b4bece284a", "http://filestoresg1.beetalkmobile.com:8081/file/c3a48c07c3093a8036c75b6228a69e6a", "http://filestoresg1.beetalkmobile.com:8081/file/61e5bfeab615bc9e3104a5cfc6873096", "http://filestoresg1.beetalkmobile.com:8081/file/2de37238608c77bbd11e4da894e3c86b", "http://filestoresg1.beetalkmobile.com:8081/file/2a77a21b700f18e53783531758ac1329"], "urls": [], "title": "\u9ad8\u6a39\u82b1\u6d77"}, "threadStatus": 0, "regionId": 886, "barStatus": 0, "barId": 77, "postBy": {"utc": 1453282660000, "level": 6, "location": "\u9ad8\u96c4\u5e02\u00b7\u53f0\u7063", "avatar": "http://filestoresg1.beetalkmobile.com:8081/file/-9213451139432759023", "name": "\u7d00\u79cb\u7bf2"}, "id": 2944660}
