{"forum": {"content": "\u5b9c\u862d", "images": ["http://filestoresg1.beetalkmobile.com:8081/file/9a57dfad9856c7b00e55abb8987caeaf", "http://filestoresg1.beetalkmobile.com:8081/file/b24e9ce87bdc23498c4189ffa86aa9a7", "http://filestoresg1.beetalkmobile.com:8081/file/776485ee3a3a1bd270bc88c536cff534"], "urls": [], "title": "\u4e00\u7bc0\u5169\u7aff12\u65a4 \uff08\u6bcd\u8766\uff09"}, "threadStatus": 0, "regionId": 886, "barStatus": 0, "barId": 723, "postBy": {"utc": 1446340074000, "level": 2, "location": "\u65b0\u5317\u5e02\u00b7\u53f0\u7063", "avatar": "http://filestoresg1.beetalkmobile.com:8081/file/7913225876422644351", "name": "\u5609"}, "id": 2440219}
