{"forum": {"content": "\u5206\u624b\u4e00\u500b\u6708\u4e86\u5979\u8aaa\u5979\u73fe\u5728\u53ea\u60f3\u7576\u670b\u53cb<br />\u8aaa\u6211\u53ef\u4ee5\u7b49\u9084\u662f\u53ef\u4ee5\u8ffd\u5979<br />\u53ea\u662f\u4e0d\u77e5\u9053\u6211\u8ffd\u4e0d\u8ffd\u7684\u5230\u800c\u5df2", "images": ["http://filestoresg1.beetalkmobile.com:8081/file/4a4429f78659f9c51a0c229bbe8f4247", "http://filestoresg1.beetalkmobile.com:8081/file/ead147489df83bcf439be432d355aa68"], "urls": [], "title": "\u7b49\u5f85\u662f\u5426\u5f88\u5fc3\u75db...\u5206\u624b\u771f\u7684\u53ef\u4ee5\u7576\u670b\u53cb\u55ce\uff1f\u5979\u8aaa\u5979\u5fc3\u88e1\u9084\u662f\u6709\u7599\u7629"}, "threadStatus": 1, "regionId": 886, "barStatus": 0, "barId": 18, "postBy": {"utc": 1453555736000, "level": 10, "location": "\u5b9c\u862d\u7e23\u00b7\u53f0\u7063", "avatar": "http://filestoresg1.beetalkmobile.com:8081/file/-4986747024279652349", "name": "\u6ef4\u903c\u5152"}, "id": 2965173}
