{"forum": {"content": "\u66fe\u4ee5\u70ba\u81ea\u5df1\u662f\u5e78\u798f\u7684<br /><br />\u771f\u7684\u53ea\u662f\u66fe\u4ee5\u70ba\u3002", "images": ["http://filestoresg1.beetalkmobile.com:8081/file/023046259e1388284bc79d2864b50ab1"], "urls": [], "title": "\u66fe\u4ee5\u70ba"}, "threadStatus": 1, "regionId": 886, "barStatus": 0, "barId": 24, "postBy": {"utc": 1451382161000, "level": 3, "location": "\u65b0\u5317\u5e02\u00b7\u53f0\u7063", "avatar": "http://filestoresg1.beetalkmobile.com:8081/file/-5580670210980174126", "name": "\ud83d\udca7\u773c\u6dda\ud83d\udca6"}, "id": 2808256}
