{"forum": {"content": "\u6211\u662f\u7d05\u8863\u5c0f\u5973\u5b69", "images": ["http://filestoresg1.beetalkmobile.com:8081/file/d3fede802a3369876b7338a975691a36", "http://filestoresg1.beetalkmobile.com:8081/file/fc34c37054a1b13224afbf8b8f1aeed0", "http://filestoresg1.beetalkmobile.com:8081/file/746dcc936c82f1812feca79a90b64fe0", "http://filestoresg1.beetalkmobile.com:8081/file/3389c27dfe0c53a3ecb28f083866f6d3"], "urls": [], "title": "\u55e8 "}, "threadStatus": 1, "regionId": 886, "barStatus": 0, "barId": 4, "postBy": {"utc": 1450452206000, "level": 12, "location": "\u53f0\u5357\u5e02\u00b7\u53f0\u7063", "avatar": "http://filestoresg1.beetalkmobile.com:8081/file/-4110561602795459131", "name": "\ud83d\udc31"}, "id": 2741872}
