{"forum": {"content": "\u4e2d\u5348\u8981\u5403\u559c\u9152\uff0c\u5148\u4f86\u676f\u9192\u8166\u7684\u98f2\u6599", "images": ["http://filestoresg1.beetalkmobile.com:8081/file/ac38a926fef024f942e18ad2011da3d8"], "urls": [], "title": "\u4eca\u5929\u8981\u5403\u559c\u9152"}, "threadStatus": 0, "regionId": 886, "barStatus": 0, "barId": 746, "postBy": {"utc": 1449370627000, "level": 12, "location": "\u53f0\u5357\u5e02\u00b7\u53f0\u7063", "avatar": "http://filestoresg1.beetalkmobile.com:8081/file/-3107273733847782695", "name": "\u9ec3\u5927\u5a55"}, "id": 2659505}
