{"forum": {"content": "\u8208\u8da3\u597d\u50cf\u8d8a\u8001\u8d8a\u55ae\u4e00<br />\u73fe\u5728\u6c92\u4e8b\u5065\u8eab\u770b\u96fb\u5f71\u627e\u7f8e\u98df<br />\u597d\u50cf\uff0c\u5c31\u6c92\u4e86\u3002<br /><br />\u96e3\u9053\u4e5f\u8981\u958b\u59cb\u62c9\u8b66\u5831\u4e86\u55ce\uff1f", "images": ["http://filestoresg1.beetalkmobile.com:8081/file/28c3b8009c278d3d751d21d672b51260", "http://filestoresg1.beetalkmobile.com:8081/file/6ea4de456874ad8aebe0d0d9021b7656", "http://filestoresg1.beetalkmobile.com:8081/file/1156958f4c274fb1d13ebb1f3ec51422", "http://filestoresg1.beetalkmobile.com:8081/file/f6e03375395464c612f26fed5f23cea6"], "urls": [], "title": "30\u62c9\u8b66\u5831\uff0c\u55e1\u55e1\u55e1\ud83d\ude35\ud83d\ude35\ud83d\ude35"}, "threadStatus": 0, "regionId": 886, "barStatus": 0, "barId": 33, "postBy": {"utc": 1449297811000, "level": 2, "location": "\u65b0\u5317\u5e02\u00b7\u53f0\u7063", "avatar": "http://filestoresg1.beetalkmobile.com:8081/file/4293539036306830931", "name": "\u3053\u3093\u306b\u3061\u306f\u3002Joe"}, "id": 2654426}
