{"forum": {"content": "\u96e3\u5f97\u9019\u9ebc\u7d20", "images": ["http://filestoresg1.beetalkmobile.com:8081/file/1edcb8dbfff7c7acc5bc7654396fe4ef"], "urls": [], "title": "\u7d20"}, "threadStatus": 1, "regionId": 886, "barStatus": 0, "barId": 20, "postBy": {"utc": 1451299606000, "level": 8, "location": "\u53f0\u5317\u5e02\u00b7\u53f0\u7063", "avatar": "http://filestoresg1.beetalkmobile.com:8081/file/-7226051989510846634", "name": "\u1d30\u1d35\u02e2\u1d2c\u1d3e\u1d3e\u1d31\u1d2c\u1d3f"}, "id": 2802294}
