{"forum": {"content": "\u651d\u5f71\u5bb6\u7684\u5929\u5802", "images": ["http://filestoresg1.beetalkmobile.com:8081/file/9e49c4ac32a1470058e28d1bb6462717", "http://filestoresg1.beetalkmobile.com:8081/file/0db107a59a66ef1fedb690613ade8906", "http://filestoresg1.beetalkmobile.com:8081/file/ba21b041b3868d92a8eed940c7f3c995", "http://filestoresg1.beetalkmobile.com:8081/file/f2fbda9739b5c0ea88a445000b3ed70f", "http://filestoresg1.beetalkmobile.com:8081/file/07c6ec968ff04125ab665d826d23dc4a", "http://filestoresg1.beetalkmobile.com:8081/file/b533d7c8c4ec05110ff9f757ca76379e"], "urls": [], "title": "\u5ddd\u3002\u7a3b\u57ce\u4e9e\u4e01 2"}, "threadStatus": 0, "regionId": 886, "barStatus": 0, "barId": 77, "postBy": {"utc": 1447833687000, "level": 2, "location": "\u6d59\u6c5f\u7701\u00b7\u4e2d\u56fd", "avatar": "http://filestoresg1.beetalkmobile.com:8081/file/7975760598596532851", "name": "KC"}, "id": 2549306}
