{"forum": {"content": "\u9019\u50f9\u9322\ud83d\ude31", "images": ["http://filestoresg1.beetalkmobile.com:8081/file/dc185b05918853373fd69ae449fb1643"], "urls": [], "title": "\u9999\u6e2f\uff5e\u8c6a\u5927\u5927\ud83c\udf56\ud83c\udf56"}, "threadStatus": 0, "regionId": 886, "barStatus": 0, "barId": 98, "postBy": {"utc": 1450787934000, "level": 7, "location": "\u6843\u5712\u5e02\u00b7\u53f0\u7063", "avatar": "http://filestoresg1.beetalkmobile.com:8081/file/22001232426461465", "name": "\u9ebb\u7cec\ud83d\udc07\u7537"}, "id": 2765800}
