{"forum": {"content": "\u3127\u53e5\u8a71\u5e36\u8d70\u4ee5\u67d4\u311a\u311a", "images": ["http://filestoresg1.beetalkmobile.com:8081/file/1155edc8b4d893f827ea5657ed1395e6"], "urls": [], "title": "\u4e00\u53e5\u8a71\u80fd\u5e36\u8d70\u6211"}, "threadStatus": 0, "regionId": 886, "barStatus": 0, "barId": 205, "postBy": {"utc": 1441556067000, "level": 0, "location": "\u82b1\u84ee\u7e23\u00b7\u53f0\u7063", "avatar": "http://filestoresg1.beetalkmobile.com:8081/file/-2916375414294677459", "name": "\u4ee5\u67d4"}, "id": 2067884}
