{"forum": {"content": "\u65e5\u672c\u670b\u53cb\u7684\u670b\u53cb\u8acb\u5403\u98ef\uff0c\u90a3\u76e4\u7d05\u8089\u662f......\u751f__\u8089\ud83d\ude31", "images": ["http://filestoresg1.beetalkmobile.com:8081/file/213b6d0b5669d6cf160dcc55b852ab5a", "http://filestoresg1.beetalkmobile.com:8081/file/258189c752f16d3b8f0cd6fc75813406", "http://filestoresg1.beetalkmobile.com:8081/file/582cb5e90c7c372ef7e9aea7b1f7ce29", "http://filestoresg1.beetalkmobile.com:8081/file/a95f3fe607ea972070512d310815af01", "http://filestoresg1.beetalkmobile.com:8081/file/49c5354d23010d83673d5ccb85d9a10f"], "urls": [], "title": "\u9053\u9813\u5d1b"}, "threadStatus": 0, "regionId": 886, "barStatus": 0, "barId": 87, "postBy": {"utc": 1442543944000, "level": 2, "location": "\u53f0\u5317\u5e02\u00b7\u53f0\u7063", "avatar": "http://filestoresg1.beetalkmobile.com:8081/file/-5964238144833703424", "name": "Alex"}, "id": 2142840}
