{"forum": {"content": "\u7537\u670b\u53cb\u6d88\u5931<br />\u662f\u4e0d\u662f\u4ee3\u8868\u4e0d\u6703\u56de\u4f86\u4e86?", "images": ["http://filestoresg1.beetalkmobile.com:8081/file/14176b1f25e2b71de215628208d7896c"], "urls": [], "title": "\u6c42\u89e3"}, "threadStatus": 1, "regionId": 886, "barStatus": 0, "barId": 13, "postBy": {"utc": 1448095713000, "level": 2, "location": "\u65b0\u5317\u5e02\u00b7\u53f0\u7063", "avatar": "http://filestoresg1.beetalkmobile.com:8081/file/-6510081894848301633", "name": "\u5c0f\u7c73"}, "id": 2568342}
