{"forum": {"content": "\u4e0d\u8981\u81ea\u4ee5\u70baPO\u6587\u7f3a\u7537\u53cb \u6709\u4e00\u5806\u56de\u61c9 \u5c31\u81ea\u4ee5\u70ba\u88ab\u6367\u6210\u5973\u795e\u4e86<br />\u4e8b\u5be6\u4e0a\u59b3\u771f\u7684\u7f3a\u55ce\uff1f<br />\u5c31\u7b97\u662f\u771f\u7684\u4e5f\u53ea\u6709\u5c11\u90e8\u4efd\u5427<br />-----------------<br />[\u6211\u723dPO\u5ee2\u6587]<br />[\u5973\u7e69\u5011\u6211\u6b20\u5634]<br />[\u59b3\u5011\u6562\u8aaa\u4e0d\u662f\u55ce\uff1f]", "images": ["http://filestoresg1.beetalkmobile.com:8081/file/d2f8c2d31fd3a9be50e514b4c40b6e7c"], "urls": [], "title": "\u5973\u795e\u7537\u795e\u5011\u5165\u5167\u627e\u4f4d\u5b50\u5750"}, "threadStatus": 0, "regionId": 886, "barStatus": 0, "barId": 205, "postBy": {"utc": 1452374431000, "level": 3, "location": "\u9ad8\u96c4\u5e02\u00b7\u53f0\u7063", "avatar": "http://filestoresg1.beetalkmobile.com:8081/file/-8645441236051071449", "name": "\u5b98\u4ec1"}, "id": 2877706}
