{"forum": {"content": "\u771f\u5fc3\u89ba\u5f972\u958b\u982d\u4e4b\u5f8c\u6642\u9593\u90fd\u904e\u7684\u597d\u5feb \u8a0e\u53ad", "images": ["http://filestoresg1.beetalkmobile.com:8081/file/2da83ea7b0f08307d440b0eb6d57a8f1"], "urls": [], "title": "\u898121\u4e86"}, "threadStatus": 1, "regionId": 886, "barStatus": 0, "barId": 4, "postBy": {"utc": 1451461040000, "level": 8, "location": "\u53f0\u4e2d\u5e02\u00b7\u53f0\u7063", "avatar": "http://filestoresg1.beetalkmobile.com:8081/file/-823721124505888508", "name": "\u59ae\u59ae"}, "id": 2813660}
