{"forum": {"content": "\u60f3\u627e\u500b\u6709\u76f8\u540c\u60f3\u6cd5\u7684\u5973\u4eba\u5f88\u96e3\u55ce\uff01\u9084\u662f\u9019\u88e1\u6c92\u6709\u60f3\u5b89\u5b9a\u7684\u5973\u4eba\uff01\u6211\u61c9\u8a72\u662f\u4e0d\u81f3\u65bc\u5dee\u5230\u54ea\u88e1\u5427\uff01\u6709\u60f3\u5b89\u5b9a\u7684\u5973\u4eba\u9858\u610f\u8207\u6211\u5f9e\u670b\u53cb\u958b\u59cb\u55ce", "images": ["http://filestoresg1.beetalkmobile.com:8081/file/b1d1916045e6d8081ac23e1fdaeb0fb8", "http://filestoresg1.beetalkmobile.com:8081/file/54eaffeb01ac09035ecec8d82bb4306d"], "urls": [], "title": "\u5c0b\u627e\u60f3\u5b89\u5b9a\u7684\u5973\u4eba"}, "threadStatus": 0, "regionId": 886, "barStatus": 0, "barId": 205, "postBy": {"utc": 1444221144000, "level": 11, "location": "\u53f0\u5317\u5e02\u00b7\u53f0\u7063", "avatar": "http://filestoresg1.beetalkmobile.com:8081/file/-1652883733960851504", "name": "\u5c0b\u627e\u4e00\u500b\u59b3(\u963f\u6b23)"}, "id": 2271496}
