{"forum": {"content": "\u76ee\u524d\u8173\u8e0f\u8eca\u74b0\u5cf6\u5230\u9ad8\u96c4\u5566\uff0c\u60f3\u8acb\u5927\u5bb6\u63a8\u85a6\u4e00\u4e0b\u597d\u5403\uff0c\u597d\u770b\uff0c\u597d\u73a9\u7684\u5730\u65b9<br />\u9084\u6709\u5f88\u91cd\u8981\u7684\u662f\u6211\u6c99\u767c\u885d\u6d6a<br />\u8acb\u597d\u5fc3\u4eba\u6536\u7559\u6211\u4e00\u665a\u5427<br />I can do anything!!!!", "images": ["http://filestoresg1.beetalkmobile.com:8081/file/7fdc694b181eed2619f5a8dc0f0d8655", "http://filestoresg1.beetalkmobile.com:8081/file/7a29615a927b540b0819e07f9e3e3edf"], "urls": [], "title": "\u55ae\u8eca\u74b0\u5cf6\u6c42\u6551(\u9ad8\u96c4\uff0c\u5c4f\u6771\uff0c\u53f0\u6771)"}, "threadStatus": 0, "regionId": 886, "barStatus": 0, "barId": 85, "postBy": {"utc": 1441875458000, "level": 1, "location": "\u9ad8\u96c4\u5e02\u00b7\u53f0\u7063", "avatar": "http://filestoresg1.beetalkmobile.com:8081/file/8551702379266876679", "name": "Matt"}, "id": 2092087}
