{"forum": {"content": "\u6211\u7b97\u578b\u7537\u6216\u5e25\u54e5\u55ce\uff1f~", "images": ["http://filestoresg1.beetalkmobile.com:8081/file/7d45e1fe486ee8233003abcc1d7d9832", "http://filestoresg1.beetalkmobile.com:8081/file/7258ed3620bded891f1d06a07e7c41b8", "http://filestoresg1.beetalkmobile.com:8081/file/acf3b7dbaccdbe42d2e21e0ec14559e1", "http://filestoresg1.beetalkmobile.com:8081/file/391c9903a75d2da1b6146b508321d2e6", "http://filestoresg1.beetalkmobile.com:8081/file/327adbfd6f73453dfa41788416aeb380", "http://filestoresg1.beetalkmobile.com:8081/file/32e88cb1bb4cd0c1c39f1fb3080434c7"], "urls": [], "title": "\u807d\u8aaa\u9019\u88e1\u662f\u578b\u7537\u5e25\u54e5\u5340"}, "threadStatus": 1, "regionId": 886, "barStatus": 0, "barId": 33, "postBy": {"utc": 1449842564000, "level": 3, "location": "\u53f0\u5357\u5e02\u00b7\u53f0\u7063", "avatar": "http://filestoresg1.beetalkmobile.com:8081/file/8831469812861788012", "name": "\u6631\u8aa0"}, "id": 2696471}
