{"forum": {"content": "\u4f86\u4f86\u4f86\uff0c\u4ea4\u500b\u670b\u53cb\u561b<br />\u6211\u53c8\u4e0d\u6703\u54ac\u4eba xD<br /><br />\u6709\u6642\u9593\u4e00\u8d77\u804a\u5929<br />\u6709\u6642\u9593\u4e00\u8d77\u6253\u7403<br /><br />\u4e0d\u6703\u5403\u4eba\u7684\uff0c\u653e\u5fc3\uff1a\uff09", "images": ["http://filestoresg1.beetalkmobile.com:8081/file/d2f73a79bb804770d610a9ca929905e7", "http://filestoresg1.beetalkmobile.com:8081/file/265a6495a5108fb29c90159beccd84b5"], "urls": [], "title": "\u563f\uff5e"}, "threadStatus": 1, "regionId": 886, "barStatus": 0, "barId": 205, "postBy": {"utc": 1445336367000, "level": 6, "location": "\u53f0\u5357\u5e02\u00b7\u53f0\u7063", "avatar": "http://filestoresg1.beetalkmobile.com:8081/file/1541926522845815480", "name": "\u3010\u7d05\u8863\u5c0f\u599e\u9b5a\u3011"}, "id": 2361560}
