{"forum": {"content": "\u60b6...", "images": ["http://filestoresg1.beetalkmobile.com:8081/file/58c4596922b0822b9314c4102ba86ad2", "http://filestoresg1.beetalkmobile.com:8081/file/d17782ae6f78613c93845d5a210a920e", "http://filestoresg1.beetalkmobile.com:8081/file/f8f1e0736dfe9e8c58f905b928a3f2fe", "http://filestoresg1.beetalkmobile.com:8081/file/64b88cd5e1fd024f53212e64cfacd784"], "urls": [], "title": "\u5be7\u975c\u611f\u89ba!"}, "threadStatus": 1, "regionId": 886, "barStatus": 0, "barId": 33, "postBy": {"utc": 1449497943000, "level": 1, "location": "\u65b0\u7af9\u7e23\u00b7\u53f0\u7063", "avatar": "http://filestoresg1.beetalkmobile.com:8081/file/-3154951843446983494", "name": "\u67ef\u921c\u85b0"}, "id": 2670223}
