{"forum": {"content": "\u6211\u4e4b\u524d\u6709\u6d17\u51b7\u6c34\u6fa1\u7684\u7fd2\u6163\r<br />\r<br />\u4e4b\u524d\u662f\u8a8d\u70ba\u53ef\u4ee5\u5f37\u5065\u8eab\u9ad4\r<br />\r<br />\u524d\u5e7e\u5929\u9592\u4f86\u7121\u4e8b\u8ddf\u4eba\u804a\u4e86\u4e00\u4e0b\r<br />\r<br />\u53c8\u6709\u4eba\u8aaa\u9019\u5c0d\u8eab\u9ad4\u4e0d\u597d\r<br />\r<br />\u53bb\u7db2\u8def\u770b\u4e86\u4e4b\u5f8c\u597d\u50cf\u4e5f\u662f\u4e8c\u6d3e\u8aaa\u6cd5\r<br />\r<br />\u60f3\u8acb\u6559\u6d17\u51b7\u6c34\u6fa1\u5c0d\u8eab\u9ad4\u7684\u597d\u58de\u6709\u7d93\u904e\u7814\u7a76\u8b49\u5be6\u7684\u8cc7\u6599\u55ce\uff1f\r<br />\r<br />\u9084\u662f\u6d17\u7684\u65b9\u6cd5\u554f\u984c?", "images": ["http://filestoresg1.beetalkmobile.com:8081/file/bb84b9b177c510a4d9932babd54f501b"], "urls": [], "title": "\u51b7\u6c34\u6fa1\u512a\u52a3\uff1f"}, "threadStatus": 0, "regionId": 886, "barStatus": 0, "barId": 771, "postBy": {"utc": 1450158253000, "level": 0, "location": "", "avatar": "http://filestoresg1.beetalkmobile.com:8081/file/-2677791299579295422", "name": "Momo"}, "id": 2719991}
