{"forum": {"content": "\u6211\u5916\u8868\u5f88\u51f6\uff0c\u4f46\u90a3\u53ea\u662f\u6211\u7684\u507d\u88dd\uff0c\u8acb\u7d66\u500b\u6a5f\u6703\u548c\u6211\u505a\u670b\u53cb\u5427\uff0c\u4f4f\u5609\u7fa9\u7684\u7d04\u51fa\u4f86\u898b\u9762\u8a8d\u8b58\u5427\ud83d\ude00\ud83d\ude00", "images": ["http://filestoresg1.beetalkmobile.com:8081/file/0ccf1d00903d91f92605c5e27fe31af9"], "urls": [], "title": "\u55ae\u8eab\u4ea4\u670b\u53cb\ud83d\udc9d\ud83d\udc9d"}, "threadStatus": 1, "regionId": 886, "barStatus": 0, "barId": 205, "postBy": {"utc": 1440968369000, "level": 3, "location": "\u5609\u7fa9\u5e02\u00b7\u53f0\u7063", "avatar": "http://filestoresg1.beetalkmobile.com:8081/file/2842874176136142243", "name": "\u6960"}, "id": 2022133}
