{"forum": {"content": "\u65b0\u7af9\u4eba17\u6b72\u53ef\u611b\u7684T<br />\u6709\u6279\u60f3\u8a8d\u8b58\u55ce\uff1f<br />\u4f86 \u6211\u5011\u4f86\u804a\u804a", "images": ["http://filestoresg1.beetalkmobile.com:8081/file/193c6888e4d2f457eede2b64b5f2fe66"], "urls": [], "title": "\u8cf4 513864187"}, "threadStatus": 0, "regionId": 886, "barStatus": 0, "barId": 20, "postBy": {"utc": 1447176597000, "level": 3, "location": "\u65b0\u7af9\u7e23\u00b7\u53f0\u7063", "avatar": "http://filestoresg1.beetalkmobile.com:8081/file/-6967705238264090880", "name": "Jay"}, "id": 2502472}
