{"forum": {"content": "\u4eca\u5e74\u70e4\u8089\u70e4\u5230\u725b\u6392\ud83d\udc02\u771f\u7684\u7c89\u904e\u766e\u6b38\uff0c\u4e0b\u6b21\u6211\u60f3\u4f86\u9ede\u4e0d\u4e00\u6a23\u7684\uff0c\u70e4\u9c77\u9b5a\ud83d\udc0a\u61c9\u8a72\u6703\u5f88\u8b9a\ud83d\udc4d", "images": ["http://filestoresg1.beetalkmobile.com:8081/file/bbe6b1ffc2673ad5d456bff9ff86d4b4", "http://filestoresg1.beetalkmobile.com:8081/file/f0fcbb2508ceb1ddf0a4fb757403414e"], "urls": [], "title": "\u660e\u5e74\u4e2d\u79cb\u6211\u60f3\u70e4\u9c77\u9b5a\ud83d\udc0a\u6b38...."}, "threadStatus": 0, "regionId": 886, "barStatus": 0, "barId": 98, "postBy": {"utc": 1442748248000, "level": 3, "location": "\u53f0\u5317\u5e02\u00b7\u53f0\u7063", "avatar": "http://filestoresg1.beetalkmobile.com:8081/file/-3003289621617335979", "name": "\ud83d\ude4a\u029d\u03c3h\u0438\u0438\u0443\ud83d\ude4a"}, "id": 2158610}
