{"forum": {"content": "\u4e00\u500b\u4eba\u7684\u65c5\u884c", "images": ["http://filestoresg1.beetalkmobile.com:8081/file/c8b43bc38a7fafb377abb7dbf8852ae9", "http://filestoresg1.beetalkmobile.com:8081/file/caaedd674095f02a318fe2c1a9a87d3d", "http://filestoresg1.beetalkmobile.com:8081/file/3d041d8dec55f28576c1a078c439ec3f", "http://filestoresg1.beetalkmobile.com:8081/file/4420e3d2aea0dcac438ef4c3bd9474e1", "http://filestoresg1.beetalkmobile.com:8081/file/01b30c01f3dcf3fb1fae7d8745a5d03c", "http://filestoresg1.beetalkmobile.com:8081/file/000c4ff50775f3538faa6118159b6dfd"], "urls": [], "title": "\u6162\u904a\u5317\u4eac"}, "threadStatus": 0, "regionId": 886, "barStatus": 0, "barId": 85, "postBy": {"utc": 1444275093000, "level": 2, "location": "\u65b0\u7af9\u5e02\u00b7\u53f0\u7063", "avatar": "http://filestoresg1.beetalkmobile.com:8081/file/7853140863201969913", "name": "San  \u51dd\u7d50\u5e78\u798f\u5e73\u9762\u651d\u5f71\ud83d\udcf7"}, "id": 2275344}
