{"forum": {"content": "<br />\u9ad8\u4e2d\u7562\u696d\u5f8c\u5c31\u7576\u5175<br />\u9000\u4f0d\u5f8c\u5c31\u958b\u59cb\u958b\u59cb\u5de5\u4f5c\u4e86 <br />\u73fe\u5728\u5728\u6838\u80fd\u767c\u96fb\u5ee0\u5de5\u4f5c <br />\u85aa\u6c34\u9084\u662f\u572822k<br /><br />\u984c\u5916\u8a71\uff1b\u6700\u8fd1\u611f\u60c5\u751f\u6d3b \u906d\u53d7\u56b4\u91cd\u7684\u6253\u64ca \u5973\u53cb\u8aaa \u611b\u60c5\u4ec0\u9ebc\u6771\u897f \u80fd\u5403\u561b\uff1f <br />", "images": ["http://filestoresg1.beetalkmobile.com:8081/file/283ca0f593865cbb6ae67c872c0a2498"], "urls": [], "title": "82 9 6"}, "threadStatus": 1, "regionId": 886, "barStatus": 0, "barId": 748, "postBy": {"utc": 1453517308000, "level": 0, "location": "\u5c4f\u6771\u7e23\u00b7\u53f0\u7063", "avatar": "http://filestoresg1.beetalkmobile.com:8081/file/-553557923979261182", "name": "\u6e6f"}, "id": 2961959}
