{"forum": {"content": "\u8a72\u51fa\u73fe\u4e86\u5427", "images": ["http://filestoresg1.beetalkmobile.com:8081/file/54dcdfb650223c3d6131ae5ac3e75ab3"], "urls": [], "title": "32\u6b72\u4e86\u90a3\u500b\u59b3\u5728\u54ea\u5152"}, "threadStatus": 1, "regionId": 886, "barStatus": 0, "barId": 740, "postBy": {"utc": 1452348225000, "level": 9, "location": "\u53f0\u4e2d\u5e02\u00b7\u53f0\u7063", "avatar": "http://filestoresg1.beetalkmobile.com:8081/file/-8152308070463272395", "name": "Chou"}, "id": 2875759}
