{"forum": {"content": "\u65b0\u4f86\u7684\u5bf6\u8c9d\u5011~\ud83d\ude18\ud83d\ude18", "images": ["http://filestoresg1.beetalkmobile.com:8081/file/aa2810f9a14766a30675417cdb5da271", "http://filestoresg1.beetalkmobile.com:8081/file/c6dda4b4c116021f4b51fa2f7f81fbce", "http://filestoresg1.beetalkmobile.com:8081/file/3a90571dc6395c5890670190cfc260bf", "http://filestoresg1.beetalkmobile.com:8081/file/fd447c715871d75b18db2fdd92706dab"], "urls": [], "title": "\u65b0\u4f86\u7684\u5bf6\u8c9d\u5011"}, "threadStatus": 1, "regionId": 886, "barStatus": 0, "barId": 105, "postBy": {"utc": 1449282339000, "level": 3, "location": "", "avatar": "http://filestoresg1.beetalkmobile.com:8081/file/-4436143488204431330", "name": "\ud83d\udc8b\u661f\u91c7\u6069\ud83d\udc8b"}, "id": 2653226}
