{"forum": {"content": "\u5361\u62c9OK\u7248\u7684\u5929\u540e \u8ddf\u6b61\u6b4c\u7248\u7684\u5dee\u5f88\u591a \u73fe\u5834\u5be6\u529b\u6d3e\u6bd4\u8f03\u4e0d\u592a\u6703\u5531\u6b61\u6b4c\u7684\u7248 \u56e0\u70ba\u6536\u97f3\u592a\u654f\u611f \u5e0c\u671b\u5927\u5bb6\u5e73\u8a55\u5206\u4e00\u4e0b", "images": [], "urls": [{"url": "http://17sing.tw/song//1883216", "thumbUrl": "http://119.81.237.155:8081/group8/M00/0E/E4/d1HtmlY2t5uAGxY_AABjdjBEQkI854.png", "description": "", "title": "\u6e05\u55315\u5206\u9418-\u7956\u6b38"}], "title": "\u5361\u62c9\u7248\u8ddf\u6b61\u6b4c\u7248\u5dee\u5f88\u591a \u4f46\u662f\u73fe\u5834\u7684\u9084\u662f\u6bd4\u8f03\u80fd\u5920\u5531\u51fa\u81ea\u5df1\u7684\u611f\u89ba"}, "threadStatus": 0, "regionId": 886, "barStatus": 0, "barId": 54, "postBy": {"utc": 1446430886000, "level": 1, "location": "\u53f0\u6771\u7e23\u00b7\u53f0\u7063", "avatar": "http://filestoresg1.beetalkmobile.com:8081/file/-3271153730413031933", "name": "\u5ff5\u5ff5"}, "id": 2446865}
