{"forum": {"content": "\u80fd\u7d66\u6211\u6eff\u6eff\u7684\u611b<br /><br />\u611f\u53d7\u5230\u6bcf\u5929\u88ab\u5e78\u798f\u5305\u570d<br /><br />\u611f\u53d7\u5230\u4ed6\u5805\u5b9a\u4e0d\u8b8a\u7684\u611f\u60c5<br /><br />\u4e0d\u6703\u8f15\u6613\u653e\u68c4\u611b\u4f60\u7684\u4fe1\u5ff5", "images": ["http://filestoresg1.beetalkmobile.com:8081/file/885a225e33f76e103bbe8f741bc19763", "http://filestoresg1.beetalkmobile.com:8081/file/df8da829e351bb83472829abaa8532b3", "http://filestoresg1.beetalkmobile.com:8081/file/2ae9de52f46e54cd61440ad1ee4f0824", "http://filestoresg1.beetalkmobile.com:8081/file/15c90c1b360d786800a3cb278575d2d6", "http://filestoresg1.beetalkmobile.com:8081/file/4a22773f644d529d212adf9fae601d82"], "urls": [], "title": "\u8ab0\u611b\u6211"}, "threadStatus": 1, "regionId": 886, "barStatus": 0, "barId": 205, "postBy": {"utc": 1448987368000, "level": 0, "location": "", "avatar": "http://filestoresg1.beetalkmobile.com:8081/file/-2791528080637748050", "name": "\u2734Space\u2734"}, "id": 2633306}
