{"forum": {"content": "\u6211\u5462\uff01<br />\u5f88\u6162\u719f<br />\u5f88\u4e0d\u77e5\u9053\u8981\u600e\u9ebc\u804a\u624d\u71b1\u7d61<br />\u5230\u5e95\u8a72\u600e\u9ebc\u8fa6\u624d\u597d\ud83d\ude25", "images": ["http://filestoresg1.beetalkmobile.com:8081/file/8a3e4a32986e85e359000bedbfed36af"], "urls": [], "title": "\u5c6c\u65bc\u6162\u719f\u4eba"}, "threadStatus": 0, "regionId": 886, "barStatus": 0, "barId": 20, "postBy": {"utc": 1446656754000, "level": 3, "location": "\u9ad8\u96c4\u5e02\u00b7\u53f0\u7063", "avatar": "http://filestoresg1.beetalkmobile.com:8081/file/-7412081659894897135", "name": "\u8036\u563f"}, "id": 2464398}
