{"forum": {"content": "BJS", "images": ["http://filestoresg1.beetalkmobile.com:8081/file/f4d9356357178d54ad9f4206eeee2c5d"], "urls": [], "title": "\u4e0d\u8212\u670d"}, "threadStatus": 1, "regionId": 886, "barStatus": 0, "barId": 391, "postBy": {"utc": 1452920581000, "level": 8, "location": "\u53f0\u5317\u5e02\u00b7\u53f0\u7063", "avatar": "http://filestoresg1.beetalkmobile.com:8081/file/218726962613541637", "name": "\ud83c\uddf9\ud83c\uddfc\u621a\u79e6\u6c0f\ud83c\uddf0\ud83c\udded"}, "id": 2917413}
