{"forum": {"content": "\u8a8d\u8b58\u4e0b\u5427\uff01\u670b\u53cb\u5011", "images": ["http://filestoresg1.beetalkmobile.com:8081/file/e73d696d542f5e9e4cf7d2cae7644a0c"], "urls": [], "title": "\u7de3\u4f86\uff0c\u907a\u5931\u4e86\u59b3"}, "threadStatus": 1, "regionId": 886, "barStatus": 0, "barId": 205, "postBy": {"utc": 1448734952000, "level": 2, "location": "\u53f0\u5317\u5e02\u00b7\u53f0\u7063", "avatar": "http://filestoresg1.beetalkmobile.com:8081/file/6505168192913204213", "name": "\u5c0f\u8d85"}, "id": 2614785}
