{"forum": {"content": "\u5f9e\u51fa\u751f\u90a3\u4e00\u79d2\u958b\u59cb\uff0c\u5c31\u55ae\u8eab25\u5e74\u4e86\u3002<br />\u662f\u4e0d\u597d\u627e\u55ce\uff1f\u9084\u662f.......", "images": ["http://filestoresg1.beetalkmobile.com:8081/file/ec0dc9bc4ebb9449b87920bf5c3c55c6"], "urls": [], "title": "\u55ae\u8eab\uff1f"}, "threadStatus": 1, "regionId": 886, "barStatus": 0, "barId": 205, "postBy": {"utc": 1440865789000, "level": 6, "location": "\u65b0\u7af9\u5e02\u00b7\u53f0\u7063", "avatar": "http://filestoresg1.beetalkmobile.com:8081/file/7535228073122985984", "name": "\u552fwei"}, "id": 2014199}
