{"forum": {"content": "\u4f60\u80fd\u63a5\u53d7\u8ddf\u670b\u53cb\u7684\u524d\u7537\u53cb\u5728\u4e00\u8d77\u55ce?\r<br />\u6700\u8fd1\u9047\u5230\u7684\u554f\u984c\r<br />\u5f88\u7cfe\u7d50\u963f....\r<br />\u662f\u4e0d\u662f\u6211\u592a\u4fdd\u5b88 \u6216\u60f3\u592a\u591a\u4e86\u5462?", "images": ["http://filestoresg1.beetalkmobile.com:8081/file/2077fd006860eea4710afbe2ecbe0b5d"], "urls": [], "title": "\u771f\u5fc3\u8a71\u554f\u554f"}, "threadStatus": 0, "regionId": 886, "barStatus": 0, "barId": 767, "postBy": {"utc": 1448937500000, "level": 0, "location": "", "avatar": "http://filestoresg1.beetalkmobile.com:8081/file/-5859183102633659355", "name": "\u5c0f\u5afb"}, "id": 2628937}
