{"forum": {"content": "\u600e\u9ebc\u4e00\u76f4\u60f3<br />\u9001\u8056\u8a95\u7bc0\u79ae\u7269\u7d66\u524d\u5973\u53cb<br />\u5509<br />", "images": ["http://filestoresg1.beetalkmobile.com:8081/file/3384ebc5e1da0d68220c313c1cd01b54"], "urls": [], "title": "\u8056\u8a95\u7bc0"}, "threadStatus": 0, "regionId": 886, "barStatus": 0, "barId": 18, "postBy": {"utc": 1450750647000, "level": 5, "location": "\u53f0\u5317\u5e02\u00b7\u53f0\u7063", "avatar": "http://filestoresg1.beetalkmobile.com:8081/file/-2893741966418727221", "name": "\u5c0f\u5b97"}, "id": 2762604}
