{"forum": {"content": "\u672c\u4eba\u5f88\u5fc5\u901f\uff08\u96d6\u7136\u770b\u8d77\u4f86\u4e0d\u50cf\uff09<br />\u5927\u5bb6\u53bbktv\u90fd\u9ede\u4ec0\u9ebc<br />\u55e8\u6b4c\u60c5\u6b4c<br />\u7cb5\u8a9e\u82f1\u6587\u6b4c\u5462 \uff1f<br />\u5e2b\u723a\u5011\u7d66\u7ffb\u8b6f\u7ffb\u8b6f \uff0c\u8b1d\u8b1d \uff01", "images": ["http://filestoresg1.beetalkmobile.com:8081/file/e55e892490f330701faccf3d76a1f5d6", "http://filestoresg1.beetalkmobile.com:8081/file/a05d956d39b554a3a50f2f0c74401926", "http://filestoresg1.beetalkmobile.com:8081/file/5a1c931c0e549d4300e48bbabe46629d"], "urls": [], "title": "\u5927\u5bb6\u53bbktv\u6709\u4ec0\u9ebc\u597d\u6b4c\uff1f"}, "threadStatus": 1, "regionId": 886, "barStatus": 0, "barId": 8, "postBy": {"utc": 1444060546000, "level": 2, "location": "\u9ad8\u96c4\u5e02\u00b7\u53f0\u7063", "avatar": "http://filestoresg1.beetalkmobile.com:8081/file/5853941751177052900", "name": "\u7d05\u7b1b\u624b \ud83d\udd2b\ud83d\udd2a\ud83d\udca3\ud83d\udd27"}, "id": 2258940}
