{"forum": {"content": "\u53bb\u5e74\u8de8\u5e74\u597d\u50cf\u662f\u6253lol\u5ea6\u904e\u7684\u2026\u2026 <br />\u4eca\u5e74\u6211\u4e0d\u8981\u518d\u6253lol\u904e\u4e86\uff01\uff01\uff01 \u4e0d~~~", "images": ["http://filestoresg1.beetalkmobile.com:8081/file/c99fa54ba8575761a061771a7bbb3187"], "urls": [], "title": "\u6211\u8981\u8de8\u5e74\u2026\u2026\u6211\u4e0d\u8981\u6253lol\u4e0d\u8981\u4e0d\u8981\u2026\u2026"}, "threadStatus": 1, "regionId": 886, "barStatus": 0, "barId": 60, "postBy": {"utc": 1451532832000, "level": 3, "location": "\u53f0\u5317\u5e02\u00b7\u53f0\u7063", "avatar": "http://filestoresg1.beetalkmobile.com:8081/file/3081462704696685820", "name": "1234567"}, "id": 2818397}
