{"forum": {"content": "\u4e0a\u73ed\u597d\u7d2f\u554a\uff01\uff01<br />\u6bcf\u5929\u7ad911\u5c0f\u6642<br />\u9084\u4e0d\u4e00\u5b9a\u53ef\u4ee5\u6e96\u6642\u4e0b\u73ed\u5462\uff01\uff01", "images": ["http://filestoresg1.beetalkmobile.com:8081/file/b3b53ea4a531881298df31531d82df34", "http://filestoresg1.beetalkmobile.com:8081/file/6f801743849a9d37d4465235aaf92b5d"], "urls": [], "title": "\u597d\u7d2f\u554a"}, "threadStatus": 0, "regionId": 886, "barStatus": 0, "barId": 707, "postBy": {"utc": 1445176970000, "level": 1, "location": "\u65b0\u5317\u5e02\u00b7\u53f0\u7063", "avatar": "http://filestoresg1.beetalkmobile.com:8081/file/4377469160330761760", "name": "\u4e01\u4e01"}, "id": 2348657}
